cv_bridge/__init__.py
cv_bridge/core.py
cv_bridge/boost/__init__.py
cvbridge3-1.1.dist-info/METADATA
cvbridge3-1.1.dist-info/WHEEL
cvbridge3-1.1.dist-info/top_level.txt
cvbridge3-1.1.dist-info/RECORD
